cloudshell/__init__.py
cloudshell/shell/__init__.py
cloudshell/shell/standards/__init__.py
cloudshell/shell/standards/load_balancer/__init__.py
cloudshell/shell/standards/load_balancer/autoload_model.py
cloudshell/shell/standards/load_balancer/driver_interface.py
cloudshell/shell/standards/load_balancer/resource_config.py
tests/__init__.py
tests/cloudshell/__init__.py
tests/cloudshell/shell/__init__.py
tests/cloudshell/shell/standards/__init__.py
tests/cloudshell/shell/standards/load_balancer/__init__.py
tests/cloudshell/shell/standards/load_balancer/test_autoload_model.py
tests/cloudshell/shell/standards/load_balancer/test_driver_interface.py
tests/cloudshell/shell/standards/load_balancer/test_resource_ config.py
cloudshell_shell_load_balancer_standard-1.0.2.dist-info/METADATA
cloudshell_shell_load_balancer_standard-1.0.2.dist-info/WHEEL
cloudshell_shell_load_balancer_standard-1.0.2.dist-info/top_level.txt
cloudshell_shell_load_balancer_standard-1.0.2.dist-info/RECORD
