Metadata-Version: 2.1
Name: cloudshell-shell-load-balancer-standard
Version: 1.0.2
Summary: Load Balancer Standard
Home-page: http://www.qualisystems.com/
Author: QualiSystems
Author-email: info@qualisystems.com
Requires-Python: >=2.7, !=3.0.*, !=3.1.*, !=3.2.*, !=3.3.*, !=3.4.*, !=3.5.*, !=3.6.*, <4
Requires-Dist: cloudshell-shell-standards (<2.0,>=1.0)
